[{"uid":"vsfekfUn1","create-time":1709846448557,"edit-time":1709846448557,"title":"Anonymous",":create/user":{":user/uid":"qOD9FEJK2iZ5FORha2hSFo4Hrwo1"},":edit/user":{":user/uid":"qOD9FEJK2iZ5FORha2hSFo4Hrwo1"}},{"create-time":1709846448560,"title":"March 7th, 2024",":create/user":{":user/uid":"qOD9FEJK2iZ5FORha2hSFo4Hrwo1"},":log/id":1709846448559,"children":[{"string":"[[The Feynman Test]]","create-time":1753135755289,":block/refs":[{":block/uid":"gV5UtfImm"}],"refs":[{"uid":"gV5UtfImm"}],":create/user":{":user/uid":"qOD9FEJK2iZ5FORha2hSFo4Hrwo1"},"uid":"gJ5oQ-X2E","edit-time":1753135756265,":edit/user":{":user/uid":"qOD9FEJK2iZ5FORha2hSFo4Hrwo1"}}],"uid":"03-07-2024","edit-time":1709846448560,":edit/user":{":user/uid":"qOD9FEJK2iZ5FORha2hSFo4Hrwo1"}},{"create-time":1736553447922,"title":"January 10th, 2025",":create/user":{":user/uid":"qOD9FEJK2iZ5FORha2hSFo4Hrwo1"},":log/id":1736553447921,"children":[{"string":"[[The Great Ideas]]","create-time":1753133071132,":block/refs":[{":block/uid":"ZgKPX3pEE"}],"refs":[{"uid":"ZgKPX3pEE"}],":create/user":{":user/uid":"qOD9FEJK2iZ5FORha2hSFo4Hrwo1"},"uid":"fWuMmEdBQ","edit-time":1753135760299,":edit/user":{":user/uid":"qOD9FEJK2iZ5FORha2hSFo4Hrwo1"}}],"uid":"01-10-2025","edit-time":1736553447922,":edit/user":{":user/uid":"qOD9FEJK2iZ5FORha2hSFo4Hrwo1"}},{"create-time":1752966361602,"title":"July 19th, 2025",":create/user":{":user/uid":"qOD9FEJK2iZ5FORha2hSFo4Hrwo1"},":log/id":1752966361601,"children":[{"string":"","uid":"lvtaTI8Y9","create-time":1753133060195,"edit-time":1753135758635,":create/user":{":user/uid":"qOD9FEJK2iZ5FORha2hSFo4Hrwo1"},":edit/user":{":user/uid":"qOD9FEJK2iZ5FORha2hSFo4Hrwo1"}}],"uid":"07-19-2025","edit-time":1752966361602,":edit/user":{":user/uid":"qOD9FEJK2iZ5FORha2hSFo4Hrwo1"}},{"create-time":1752966477549,"title":"Chronological Snobbery",":create/user":{":user/uid":"qOD9FEJK2iZ5FORha2hSFo4Hrwo1"},"children":[{"string":"Metadata","create-time":1753135937210,"heading":1,":create/user":{":user/uid":"qOD9FEJK2iZ5FORha2hSFo4Hrwo1"},"children":[{"string":"Tags:: Term, Knowledge, Pride, Lewis","create-time":1753133435548,":block/refs":[{":block/uid":"TAaC7AW9W"}],"refs":[{"uid":"TAaC7AW9W"}],":create/user":{":user/uid":"qOD9FEJK2iZ5FORha2hSFo4Hrwo1"},"uid":"-sCqCJjuN","edit-time":1753133824366,":edit/user":{":user/uid":"qOD9FEJK2iZ5FORha2hSFo4Hrwo1"}}],"uid":"NnvDK6Rlb","edit-time":1753135949871,":edit/user":{":user/uid":"qOD9FEJK2iZ5FORha2hSFo4Hrwo1"}},{"string":"Explained C.S. Lewis's term \"Chronological Snobbery\" to someone again today. Lewis defines it as \"the uncritical acceptance of the intellectual climate common to our own age and the assumption that whatever has gone out of date is on that account discredited.\"","uid":"fKTHjqi9p","create-time":1753133419845,"edit-time":1753471070758,":create/user":{":user/uid":"qOD9FEJK2iZ5FORha2hSFo4Hrwo1"},":edit/user":{":user/uid":"qOD9FEJK2iZ5FORha2hSFo4Hrwo1"}},{"string":"It's a particularly insidious form of intellectual pride. It dismisses ideas simply because they're old rather than engaging with their actual merit.","uid":"3dG0o0B1n","create-time":1753133431118,"edit-time":1753133431118,":create/user":{":user/uid":"qOD9FEJK2iZ5FORha2hSFo4Hrwo1"},":edit/user":{":user/uid":"qOD9FEJK2iZ5FORha2hSFo4Hrwo1"}},{"string":"Owen Barfield helped Lewis overcome this tendency, and Lewis credits this correction as crucial to his intellectual development.","uid":"4a0xXh9fk","create-time":1753133397428,"edit-time":1753133431121,":create/user":{":user/uid":"qOD9FEJK2iZ5FORha2hSFo4Hrwo1"},":edit/user":{":user/uid":"qOD9FEJK2iZ5FORha2hSFo4Hrwo1"}}],"uid":"2pOFW_5Xx","edit-time":1753471251836,":edit/user":{":user/uid":"qOD9FEJK2iZ5FORha2hSFo4Hrwo1"}},{"create-time":1752995534669,"title":"July 20th, 2025",":create/user":{":user/uid":"qOD9FEJK2iZ5FORha2hSFo4Hrwo1"},":log/id":1752995534664,"children":[{"string":"[[Chronological Snobbery]]","create-time":1753135770442,":block/refs":[{":block/uid":"2pOFW_5Xx"}],"refs":[{"uid":"2pOFW_5Xx"}],":create/user":{":user/uid":"qOD9FEJK2iZ5FORha2hSFo4Hrwo1"},"uid":"6Q6TF_hzt","edit-time":1753471251836,":edit/user":{":user/uid":"qOD9FEJK2iZ5FORha2hSFo4Hrwo1"}}],"uid":"07-20-2025","edit-time":1752995534670,":edit/user":{":user/uid":"qOD9FEJK2iZ5FORha2hSFo4Hrwo1"}},{"create-time":1753081928023,"title":"July 21st, 2025",":create/user":{":user/uid":"qOD9FEJK2iZ5FORha2hSFo4Hrwo1"},":log/id":1753081928009,"children":[{"string":"","uid":"0mV8hBThQ","create-time":1753132824364,"edit-time":1753135768169,":create/user":{":user/uid":"qOD9FEJK2iZ5FORha2hSFo4Hrwo1"},":edit/user":{":user/uid":"qOD9FEJK2iZ5FORha2hSFo4Hrwo1"}}],"uid":"07-21-2025","edit-time":1753081928023,":edit/user":{":user/uid":"qOD9FEJK2iZ5FORha2hSFo4Hrwo1"}},{"create-time":1753133076425,"title":"The Feynman Test",":create/user":{":user/uid":"qOD9FEJK2iZ5FORha2hSFo4Hrwo1"},"children":[{"string":"Metadata","create-time":1753198326248,"heading":1,":create/user":{":user/uid":"qOD9FEJK2iZ5FORha2hSFo4Hrwo1"},"children":[{"string":"Tags:: Practice","create-time":1753133108792,":block/refs":[{":block/uid":"TAaC7AW9W"}],"refs":[{"uid":"TAaC7AW9W"}],":create/user":{":user/uid":"qOD9FEJK2iZ5FORha2hSFo4Hrwo1"},"uid":"eTg5d6bRF","edit-time":1753198279358,":edit/user":{":user/uid":"qOD9FEJK2iZ5FORha2hSFo4Hrwo1"}}],"uid":"2k1JjMIew","edit-time":1753198330845,":edit/user":{":user/uid":"qOD9FEJK2iZ5FORha2hSFo4Hrwo1"}},{"string":"Stumbled across Richard Feynman's technique for understanding: if you can't explain something simply, you don't really understand it.","uid":"oe4tZpwve","create-time":1753133093690,"edit-time":1753133093690,":create/user":{":user/uid":"qOD9FEJK2iZ5FORha2hSFo4Hrwo1"},":edit/user":{":user/uid":"qOD9FEJK2iZ5FORha2hSFo4Hrwo1"}},{"string":"This connects to Einstein's supposed quote about explaining things to a six-year-old, though that attribution is questionable.","uid":"tGmg0yf4Y","create-time":1753133096716,"edit-time":1753133096716,":create/user":{":user/uid":"qOD9FEJK2iZ5FORha2hSFo4Hrwo1"},":edit/user":{":user/uid":"qOD9FEJK2iZ5FORha2hSFo4Hrwo1"}},{"string":"The principle remains sound: true comprehension manifests in the ability to teach.","uid":"DBQTed61v","create-time":1753133078960,"edit-time":1753133096720,":create/user":{":user/uid":"qOD9FEJK2iZ5FORha2hSFo4Hrwo1"},":edit/user":{":user/uid":"qOD9FEJK2iZ5FORha2hSFo4Hrwo1"}}],"uid":"gV5UtfImm","edit-time":1753133076427,":edit/user":{":user/uid":"qOD9FEJK2iZ5FORha2hSFo4Hrwo1"}},{"uid":"0cbb4QLA_","create-time":1753133116218,"edit-time":1753471486508,"title":"Type",":create/user":{":user/uid":"qOD9FEJK2iZ5FORha2hSFo4Hrwo1"},":edit/user":{":user/uid":"qOD9FEJK2iZ5FORha2hSFo4Hrwo1"}},{"uid":"TAaC7AW9W","create-time":1753133162699,"edit-time":1753133162699,"title":"Tags",":create/user":{":user/uid":"qOD9FEJK2iZ5FORha2hSFo4Hrwo1"},":edit/user":{":user/uid":"qOD9FEJK2iZ5FORha2hSFo4Hrwo1"}},{"create-time":1753133280030,"title":"The Great Ideas",":create/user":{":user/uid":"qOD9FEJK2iZ5FORha2hSFo4Hrwo1"},"children":[{"string":"Metadata","create-time":1753198315552,"heading":1,":create/user":{":user/uid":"qOD9FEJK2iZ5FORha2hSFo4Hrwo1"},"children":[{"string":"Tags:: Term","create-time":1753133281493,":block/refs":[{":block/uid":"TAaC7AW9W"}],"refs":[{"uid":"TAaC7AW9W"}],":create/user":{":user/uid":"qOD9FEJK2iZ5FORha2hSFo4Hrwo1"},"uid":"IPYLjFKmx","edit-time":1753198297990,":edit/user":{":user/uid":"qOD9FEJK2iZ5FORha2hSFo4Hrwo1"}}],"uid":"fLTPFSaso","edit-time":1753198316420,":edit/user":{":user/uid":"qOD9FEJK2iZ5FORha2hSFo4Hrwo1"}},{"string":"Reading Mortimer Adler's introduction to the Syntopicon has me thinking about the challenge of organizing ideas across disciplines and centuries.","uid":"FZmegBPaG","create-time":1753133372617,"edit-time":1753133372617,":create/user":{":user/uid":"qOD9FEJK2iZ5FORha2hSFo4Hrwo1"},":edit/user":{":user/uid":"qOD9FEJK2iZ5FORha2hSFo4Hrwo1"}},{"string":"His concept of \"great ideas\" as recurring themes in human thought provides a useful framework for synthesis. The challenge is finding the right level of abstraction. Specific enough to be meaningful, general enough to connect across contexts.","uid":"tKc3a9Ssu","create-time":1753133291219,"edit-time":1753133372621,":create/user":{":user/uid":"qOD9FEJK2iZ5FORha2hSFo4Hrwo1"},":edit/user":{":user/uid":"qOD9FEJK2iZ5FORha2hSFo4Hrwo1"}}],"uid":"ZgKPX3pEE","edit-time":1753133280031,":edit/user":{":user/uid":"qOD9FEJK2iZ5FORha2hSFo4Hrwo1"}},{"create-time":1753134341583,"title":"Garden",":create/user":{":user/uid":"qOD9FEJK2iZ5FORha2hSFo4Hrwo1"},"children":[{"string":"[[Against Chronological Snobbery: Why Old Ideas Deserve Our Attention]]","create-time":1753471065207,":block/refs":[{":block/uid":"3irSUTq57"}],"refs":[{"uid":"3irSUTq57"}],":create/user":{":user/uid":"qOD9FEJK2iZ5FORha2hSFo4Hrwo1"},"uid":"vVHa9WhJu","edit-time":1753471066034,":edit/user":{":user/uid":"qOD9FEJK2iZ5FORha2hSFo4Hrwo1"}}],"uid":"1BrmZ_Dxw","edit-time":1753134341583,":edit/user":{":user/uid":"qOD9FEJK2iZ5FORha2hSFo4Hrwo1"}},{"create-time":1753134858372,"title":"Against Chronological Snobbery: Why Old Ideas Deserve Our Attention",":create/user":{":user/uid":"qOD9FEJK2iZ5FORha2hSFo4Hrwo1"},"children":[{"string":"Metadata","create-time":1753135819882,"heading":1,":create/user":{":user/uid":"qOD9FEJK2iZ5FORha2hSFo4Hrwo1"},"children":[{"string":"Date Created:: [[July 21st, 2025]]","create-time":1753135793068,":block/refs":[{":block/uid":"07-21-2025"},{":block/uid":"cVOKQOmgZ"}],"refs":[{"uid":"07-21-2025"},{"uid":"cVOKQOmgZ"}],":create/user":{":user/uid":"qOD9FEJK2iZ5FORha2hSFo4Hrwo1"},"uid":"fXqCOdvqW","edit-time":1753135815157,":edit/user":{":user/uid":"qOD9FEJK2iZ5FORha2hSFo4Hrwo1"}},{"string":"Date Updated:: [[July 21st, 2025]]","create-time":1753135798790,":block/refs":[{":block/uid":"07-21-2025"},{":block/uid":"PidJBsP4c"}],"refs":[{"uid":"07-21-2025"},{"uid":"PidJBsP4c"}],":create/user":{":user/uid":"qOD9FEJK2iZ5FORha2hSFo4Hrwo1"},"uid":"z_q1KcZmQ","edit-time":1753135812199,":edit/user":{":user/uid":"qOD9FEJK2iZ5FORha2hSFo4Hrwo1"}},{"string":"Type:: Term","create-time":1753134860653,":block/refs":[{":block/uid":"0cbb4QLA_"}],"refs":[{"uid":"0cbb4QLA_"}],":create/user":{":user/uid":"qOD9FEJK2iZ5FORha2hSFo4Hrwo1"},"uid":"_rV4Lyzjt","edit-time":1753471486508,":edit/user":{":user/uid":"qOD9FEJK2iZ5FORha2hSFo4Hrwo1"}},{"string":"Tags:: C.S. Lewis, Time, Progress, Knowledge, Humility","create-time":1753134878974,":block/refs":[{":block/uid":"TAaC7AW9W"}],"refs":[{"uid":"TAaC7AW9W"}],":create/user":{":user/uid":"qOD9FEJK2iZ5FORha2hSFo4Hrwo1"},"uid":"fvgKXma3i","edit-time":1753471175464,":edit/user":{":user/uid":"qOD9FEJK2iZ5FORha2hSFo4Hrwo1"}}],"uid":"hMMKjQRj9","edit-time":1753135826472,":edit/user":{":user/uid":"qOD9FEJK2iZ5FORha2hSFo4Hrwo1"}},{"string":"In our rush toward the future, we have developed what C.S. Lewis called \"[[Chronological Snobbery]]\"—the uncritical acceptance of the intellectual climate of our own age and the assumption that whatever has gone out of date is thereby discredited. This bias, while natural, represents one of the most dangerous forms of intellectual pride.","create-time":1753134937632,":block/refs":[{":block/uid":"2pOFW_5Xx"}],"refs":[{"uid":"2pOFW_5Xx"}],":create/user":{":user/uid":"qOD9FEJK2iZ5FORha2hSFo4Hrwo1"},"uid":"CYkax4FcR","edit-time":1753471265766,":edit/user":{":user/uid":"qOD9FEJK2iZ5FORha2hSFo4Hrwo1"}},{"string":"The problem is not that we value progress or appreciate contemporary insights. The problem lies in our reflexive dismissal of older ideas based solely on their age. We treat intellectual history like a simple timeline of improvement, where each generation necessarily surpasses the last in wisdom and understanding. (+1 This linear view of progress owes much to Enlightenment thinking and was reinforced by the rapid technological advances of the past two centuries.) But intellectual development is not analogous to technological advancement.","uid":"w9wUz8x62","create-time":1753134937632,"edit-time":1753136333363,":create/user":{":user/uid":"qOD9FEJK2iZ5FORha2hSFo4Hrwo1"},":edit/user":{":user/uid":"qOD9FEJK2iZ5FORha2hSFo4Hrwo1"}},{"string":"Consider the realm of ethics. Are we more virtuous than Aristotle because we live 2,400 years later? Have we solved the problems of justice more completely than Plato? Our moral insights may be different from theirs, informed by different experiences and contexts, but they are not automatically superior simply by virtue of chronological sequence.","uid":"iF7O7HKfM","create-time":1753134937632,"edit-time":1753134937632,":create/user":{":user/uid":"qOD9FEJK2iZ5FORha2hSFo4Hrwo1"},":edit/user":{":user/uid":"qOD9FEJK2iZ5FORha2hSFo4Hrwo1"}},{"string":"The danger becomes acute in academic disciplines where fashions change rapidly. A brilliant insight from 1950 may be ignored not because it has been refuted, but because it falls outside current scholarly trends. (+ Thomas Kuhn's work on paradigm shifts illustrates how scientific communities can become locked into particular ways of thinking, making older approaches invisible even when they retain value.) We lose access to hard-won wisdom because it wears an unfashionable date.","uid":"22VoaAGwS","create-time":1753134937632,"edit-time":1753136338056,":create/user":{":user/uid":"qOD9FEJK2iZ5FORha2hSFo4Hrwo1"},":edit/user":{":user/uid":"qOD9FEJK2iZ5FORha2hSFo4Hrwo1"}},{"string":"Lewis himself experienced this transformation dramatically. Before Owen Barfield challenged his chronological snobbery, Lewis dismissed medieval and Renaissance thought as primitive superstition. After overcoming this bias, he gained access to rich intellectual traditions that profoundly shaped his later work. The Chronicles of Narnia, his theological writings, and his literary criticism all bear the mark of pre-modern wisdom that his earlier self would have scorned.","uid":"IHfUKExp2","create-time":1753134937632,"edit-time":1753134937632,":create/user":{":user/uid":"qOD9FEJK2iZ5FORha2hSFo4Hrwo1"},":edit/user":{":user/uid":"qOD9FEJK2iZ5FORha2hSFo4Hrwo1"}},{"string":"This is not an argument for uncritical traditionalism. Old ideas are not valuable simply because they are old, just as new ideas are not valuable simply because they are new. The goal is discriminating judgment that evaluates ideas on their intrinsic merit rather than their temporal origin.","uid":"Y8wl8tHbD","create-time":1753134937632,"edit-time":1753134937632,":create/user":{":user/uid":"qOD9FEJK2iZ5FORha2hSFo4Hrwo1"},":edit/user":{":user/uid":"qOD9FEJK2iZ5FORha2hSFo4Hrwo1"}},{"string":"How do we cultivate this discrimination? First, by reading primary sources rather than relying solely on contemporary interpretations. Second, by asking what questions an older thinker was trying to answer before asking whether we agree with their conclusions. Third, by considering what aspects of human experience might remain constant across centuries, making ancient insights potentially relevant today.","uid":"1eqVSBtPP","create-time":1753134937632,"edit-time":1753134937632,":create/user":{":user/uid":"qOD9FEJK2iZ5FORha2hSFo4Hrwo1"},":edit/user":{":user/uid":"qOD9FEJK2iZ5FORha2hSFo4Hrwo1"}},{"string":"The stakes are higher than mere academic completeness. In our chronologically snobbish age, we risk cutting ourselves off from the accumulated wisdom of centuries. (+ G.K. Chesterton made a related point about tradition being \"the democracy of the dead\"—giving our ancestors a vote in contemporary decisions.) We treat the past as a museum of outdated curiosities rather than a library of living ideas. In doing so, we impoverish not only our understanding of where we came from, but our vision of where we might go.","uid":"MCVsQ8xKD","create-time":1753134937632,"edit-time":1753136341998,":create/user":{":user/uid":"qOD9FEJK2iZ5FORha2hSFo4Hrwo1"},":edit/user":{":user/uid":"qOD9FEJK2iZ5FORha2hSFo4Hrwo1"}},{"string":"The antidote to chronological snobbery is not chronological romanticism—the equally problematic assumption that older is automatically better. It is intellectual humility: the recognition that insight and error are distributed across all ages, including our own. Good ideas can emerge from any century, and our task is to find them wherever they lie hidden, brushing off the dust of time to examine their continuing relevance.","uid":"ikOT7UpKl","create-time":1753134937632,"edit-time":1753134937632,":create/user":{":user/uid":"qOD9FEJK2iZ5FORha2hSFo4Hrwo1"},":edit/user":{":user/uid":"qOD9FEJK2iZ5FORha2hSFo4Hrwo1"}},{"string":"In this light, engaging with older thinkers becomes an act of intellectual archaeology. We dig through unfamiliar language and obsolete contexts to uncover insights that transcend their historical moment. Sometimes we find ideas that truly belong to their age alone. But sometimes—often enough to make the effort worthwhile—we discover truths that speak across centuries with undiminished force.","uid":"lJIkYIYqN","create-time":1753134937632,"edit-time":1753134937632,":create/user":{":user/uid":"qOD9FEJK2iZ5FORha2hSFo4Hrwo1"},":edit/user":{":user/uid":"qOD9FEJK2iZ5FORha2hSFo4Hrwo1"}}],"uid":"3irSUTq57","edit-time":1753134858373,":edit/user":{":user/uid":"qOD9FEJK2iZ5FORha2hSFo4Hrwo1"}},{"uid":"cVOKQOmgZ","create-time":1753135586501,"edit-time":1753135586502,"title":"Date Created",":create/user":{":user/uid":"qOD9FEJK2iZ5FORha2hSFo4Hrwo1"},":edit/user":{":user/uid":"qOD9FEJK2iZ5FORha2hSFo4Hrwo1"}},{"uid":"PidJBsP4c","create-time":1753135593837,"edit-time":1753135593838,"title":"Date Updated",":create/user":{":user/uid":"qOD9FEJK2iZ5FORha2hSFo4Hrwo1"},":edit/user":{":user/uid":"qOD9FEJK2iZ5FORha2hSFo4Hrwo1"}},{"create-time":1753167603396,"title":"July 22nd, 2025",":create/user":{":user/uid":"qOD9FEJK2iZ5FORha2hSFo4Hrwo1"},":log/id":1753167603373,"uid":"07-22-2025","edit-time":1753167603396,":edit/user":{":user/uid":"qOD9FEJK2iZ5FORha2hSFo4Hrwo1"}},{"create-time":1753373589082,"title":"July 24th, 2025",":create/user":{":user/uid":"qOD9FEJK2iZ5FORha2hSFo4Hrwo1"},":log/id":1753373589081,"uid":"07-24-2025","edit-time":1753373589082,":edit/user":{":user/uid":"qOD9FEJK2iZ5FORha2hSFo4Hrwo1"}},{"create-time":1753426809808,"title":"July 25th, 2025",":create/user":{":user/uid":"qOD9FEJK2iZ5FORha2hSFo4Hrwo1"},":log/id":1753426809787,"uid":"07-25-2025","edit-time":1753426809809,":edit/user":{":user/uid":"qOD9FEJK2iZ5FORha2hSFo4Hrwo1"}}]